{
  "link_hash": "f7cc518f",
  "scraped_at": "260528_1238",
  "restaurant_name": "Meşhur Sarıyer Börek & Kır Pide",
  "link": "https://www.yemeksepeti.com/restaurant/wfjq/meshur-sariyer-borek-and-kir-pide",
  "categories": [
    {
      "name": "Kır Pideleri",
      "products": [
        {
          "name": "Kıymalı Kır Pidesi",
          "price": 85.0,
          "description": "Dana kıyma",
          "img": "https://images.deliveryhero.io/image/fd-tr/Products/78671065.jpg?width=128&height=128"
        },
        {
          "name": "Peynirli Kır Pidesi",
          "price": 85.0,
          "description": "Beyaz peynir",
          "img": "https://images.deliveryhero.io/image/fd-tr/Products/78671095.jpg?width=128&height=128"
        },
        {
          "name": "Patatesli Kır Pidesi",
          "price": 85.0,
          "description": "Patates",
          "img": "https://images.deliveryhero.io/image/fd-tr/Products/78671100.jpg?width=150&height=150"
        },
        {
          "name": "Kaşarlı Kır Pidesi",
          "price": 85.0,
          "description": "Kaşar peyniri",
          "img": "https://images.deliveryhero.io/image/fd-tr/Products/78671111.jpg?width=150&height=150"
        }
      ]
    },
    {
      "name": "Börekler",
      "products": [
        {
          "name": "Peynirli Su Böreği",
          "price": 212.5,
          "description": "Beyaz peynir",
          "img": "https://micro-assets.foodora.com/img/logo-simple-ys.svg"
        },
        {
          "name": "Kıymalı Kol Böreği",
          "price": 212.5,
          "description": "Dana kıyma",
          "img": "https://micro-assets.foodora.com/img/logo-simple-ys.svg"
        },
        {
          "name": "Patatesli Kol Böreği",
          "price": 212.5,
          "description": "Patates",
          "img": "https://images.deliveryhero.io/image/fd-tr/Products/78670872.jpg?width=150&height=150"
        },
        {
          "name": "Ispanaklı Kol Böreği",
          "price": 212.5,
          "description": "Ispanak",
          "img": "https://images.deliveryhero.io/image/fd-tr/Products/78670881.jpg?width=150&height=150"
        },
        {
          "name": "Peynirli Kol Böreği",
          "price": 212.5,
          "description": "Beyaz peynir",
          "img": "https://images.deliveryhero.io/image/fd-tr/Products/78670892.jpg?width=150&height=150"
        },
        {
          "name": "Küt Böreği",
          "price": 212.5,
          "description": "Tek kişilik",
          "img": "https://images.deliveryhero.io/image/fd-tr/Products/78670912.jpg?width=150&height=150"
        }
      ]
    },
    {
      "name": "Açık Karadeniz Pideler",
      "products": [
        {
          "name": "Kıymalı Cantık Pide",
          "price": 194.65,
          "description": "Dana kıyma",
          "img": "https://micro-assets.foodora.com/img/logo-simple-ys.svg"
        },
        {
          "name": "Kaşarlı Sucuklu Yumurtalı Cantık Pide",
          "price": 194.65,
          "description": "Kaşar peyniri, dana sucuk, yumurta",
          "img": "https://images.deliveryhero.io/image/fd-tr/Products/78671165.jpg?width=150&height=150"
        },
        {
          "name": "Kıymalı Kaşarlı Cantık Pide",
          "price": 194.65,
          "description": "Dana kıyma, kaşar peyniri",
          "img": "https://images.deliveryhero.io/image/global-menu-service/YS_TR/vendor/wfjq/product/87532021/e3c40434-784e-451a-ab3b-fd00da60b0d9.jpg?width=150&height=150"
        },
        {
          "name": "Kıymalı Kaşarlı Yumurtalı Cantık Pide",
          "price": 194.65,
          "description": "Dana kıyma, kaşar peyniri, yumurta",
          "img": "https://images.deliveryhero.io/image/global-menu-service/YS_TR/vendor/wfjq/product/87532034/93dbe0ff-08f5-453e-ae81-8ad9d3c2842f.jpg?width=150&height=150"
        },
        {
          "name": "Mantarlı Kaşarlı Cantık Pide",
          "price": 194.65,
          "description": "Mantar, kaşar peyniri",
          "img": "https://images.deliveryhero.io/image/fd-tr/Products/78671228.jpg?width=150&height=150"
        }
      ]
    },
    {
      "name": "İzmir Boyozlar",
      "products": [
        {
          "name": "Meşhur İzmi̇r Peyni̇rli̇ Boyoz",
          "price": 68.0,
          "description": "Peynir",
          "img": null
        },
        {
          "name": "Meşhur İzmi̇r Kıymalı Boyoz",
          "price": 68.0,
          "description": "Kıyma",
          "img": null
        },
        {
          "name": "Meşhur İzmi̇r Patatesli̇ Boyoz",
          "price": 68.0,
          "description": "Patates",
          "img": null
        }
      ]
    },
    {
      "name": "Poğaçalar & Açmalar & Simitler",
      "products": [
        {
          "name": "Meşhur Sarıyer Sade Açma",
          "price": 42.5,
          "description": "Adet servis edilir.",
          "img": "https://micro-assets.foodora.com/img/logo-simple-ys.svg"
        },
        {
          "name": "Meşhur Sarıyer Çikolatalı Açma",
          "price": 42.5,
          "description": "Adet servis edilir.",
          "img": "https://images.deliveryhero.io/image/fd-tr/Products/79141721.jpg?width=150&height=150"
        },
        {
          "name": "Meşhur Sarıyer Zeytinli Açma",
          "price": 42.5,
          "description": null,
          "img": "https://images.deliveryhero.io/image/fd-tr/Products/79141710.jpg?width=150&height=150"
        }
      ]
    },
    {
      "name": "İçecekler",
      "products": [
        {
          "name": "Cappy Karışık (33 cl.)",
          "price": 72.25,
          "description": "Kutu içecek",
          "img": "https://micro-assets.foodora.com/img/logo-simple-ys.svg"
        },
        {
          "name": "Cappy Vişne (33 cl.)",
          "price": 72.25,
          "description": "Kutu içecek",
          "img": "https://micro-assets.foodora.com/img/logo-simple-ys.svg"
        },
        {
          "name": "Fuse Tea Karpuz (33 cl.)",
          "price": 72.25,
          "description": "Kutu içecek",
          "img": "https://micro-assets.foodora.com/img/logo-simple-ys.svg"
        },
        {
          "name": "Fuse Tea Mango & Ananas (33 cl.)",
          "price": 72.25,
          "description": "Kutu içecek",
          "img": "https://images.deliveryhero.io/image/global-menu-service/YS_TR/vendor/wfjq/product/c604eba7-e01a-45c7-9d7e-da2f7d504d6a.jpg?width=150&height=150"
        },
        {
          "name": "Fuse Tea Şeftali (33 cl.)",
          "price": 72.25,
          "description": "Kutu içecek",
          "img": "https://images.deliveryhero.io/image/fd-tr/Products/78960613.jpg?width=150&height=150"
        },
        {
          "name": "Ayran (30 cl.)",
          "price": 38.25,
          "description": "Büyük boy",
          "img": "https://images.deliveryhero.io/image/global-menu-service/YS_TR/vendor/wfjq/product/6bf09d5d-31a4-48d7-8b02-22b724cdd14d.jpg?width=150&height=150"
        },
        {
          "name": "Nestle Pure Life Su (50 cl.)",
          "price": 21.25,
          "description": "Pet şişe",
          "img": null
        }
      ]
    },
    {
      "name": "Poşet",
      "products": [
        {
          "name": "Poşet",
          "price": 1.0,
          "description": "Çevre Kanunu kapsamında yapılan değişiklikle her bir plastik poşetin tüketicilere 1 TL fiyat karşılığı satılması Çevre, Şehircilik ve İklim Değişikliği Bakanlığı tarafından zorunlu hale getirilmiştir. Plastik poşet talep etmeniz halinde ürünü sepete eklemeniz gerekmektedir. Sepete eklenen her bir plastik poşet için ilgili bedel tarafınızdan tahsil edilecektir.",
          "img": "https://micro-assets.foodora.com/img/logo-simple-ys.svg"
        }
      ]
    }
  ]
}