{
  "link_hash": "956f8a76",
  "scraped_at": "260528_0125",
  "restaurant_name": "Helvacı Ali",
  "link": "https://www.yemeksepeti.com/restaurant/yijm/helvaci-ali-yijm",
  "categories": [
    {
      "name": "Popüler",
      "products": [
        {
          "name": "Dondurmalı Cennet Çamuru (Büyük Boy)",
          "price": 499.0,
          "description": "Maraş dövme dondurması üzerine; Antep fıstıklı irmik helvası",
          "img": "https://images.deliveryhero.io/image/fd-tr/Products/76302157.jpg?width=128&height=128"
        },
        {
          "name": "İrmik Helvası (500 gr.)",
          "price": 460.0,
          "description": "İsteğe göre tahin, yer fıstığı",
          "img": "https://images.deliveryhero.io/image/fd-tr/Products/71563767.jpg?width=128&height=128"
        },
        {
          "name": "Dondurmalı Lotuslu İrmik Helvası (Büyük Boy)",
          "price": 450.0,
          "description": "Tek kişilik",
          "img": "https://images.deliveryhero.io/image/fd-tr/Products/76302391.jpg?width=150&height=150"
        },
        {
          "name": "Dondurmalı Dubai Çikolatalı İrmik Helvası",
          "price": 399.0,
          "description": "Tek kişilik",
          "img": "https://images.deliveryhero.io/image/fd-tr/Products/76302389.jpg?width=150&height=150"
        },
        {
          "name": "Dondurmalı Çikolatalı İrmik Helvası (Büyük Boy)",
          "price": 349.0,
          "description": "Maraş dövme dondurması üzerine; çikolatalı irmik helvası",
          "img": "https://images.deliveryhero.io/image/fd-tr/Products/76302161.jpg?width=150&height=150"
        },
        {
          "name": "Çikolatalı İrmik Helvası (Dondurmasız) (Büyük Boy)",
          "price": 350.0,
          "description": "Tek kişilik",
          "img": "https://images.deliveryhero.io/image/fd-tr/Products/76302487.jpg?width=150&height=150"
        }
      ]
    },
    {
      "name": "Yan Ürünler",
      "products": [
        {
          "name": "Dut Pekmezi (380 gr.)",
          "price": 230.0,
          "description": "Cam şişe",
          "img": "https://micro-assets.foodora.com/img/logo-simple-ys.svg"
        },
        {
          "name": "Tahin (300 gr.)",
          "price": 230.0,
          "description": "Cam şişe",
          "img": "https://images.deliveryhero.io/image/fd-tr/Products/71564888.jpg?width=150&height=150"
        },
        {
          "name": "Keçiboynuzu Özü (380 gr.)",
          "price": 230.0,
          "description": "Cam şişe",
          "img": "https://images.deliveryhero.io/image/fd-tr/Products/71564904.jpg?width=150&height=150"
        }
      ]
    },
    {
      "name": "İrmik Helvaları",
      "products": [
        {
          "name": "Dondurmalı İrmik Helvası (Standart Boy)",
          "price": 199.0,
          "description": "Altında maraş dondurması, ceviz, tahin, yer fıstığı",
          "img": "https://micro-assets.foodora.com/img/logo-simple-ys.svg"
        },
        {
          "name": "Dondurmalı İrmik Helvası (Ekstra Boy)",
          "price": 299.0,
          "description": "Maraş dövme dondurması üzerine; sade irmik helvası",
          "img": "https://images.deliveryhero.io/image/fd-tr/Products/75732260.jpg?width=150&height=150"
        },
        {
          "name": "Dondurmalı Cennet Çamuru",
          "price": 335.0,
          "description": "Maraş dövme dondurması üzerine; Antep fıstıklı irmik helvası",
          "img": "https://images.deliveryhero.io/image/fd-tr/Products/76302155.jpg?width=150&height=150"
        },
        {
          "name": "Dondurmalı Cennet Çamuru (Büyük Boy)",
          "price": 499.0,
          "description": "Maraş dövme dondurması üzerine; Antep fıstıklı irmik helvası",
          "img": "https://images.deliveryhero.io/image/fd-tr/Products/76302157.jpg?width=150&height=150"
        },
        {
          "name": "Dondurmalı Çikolatalı İrmik Helvası",
          "price": 250.0,
          "description": "Maraş dövme dondurması üzerine; çikolatalı irmik helvası",
          "img": "https://images.deliveryhero.io/image/fd-tr/Products/76302159.jpg?width=150&height=150"
        },
        {
          "name": "Dondurmalı Çikolatalı İrmik Helvası (Büyük Boy)",
          "price": 349.0,
          "description": "Maraş dövme dondurması üzerine; çikolatalı irmik helvası",
          "img": "https://images.deliveryhero.io/image/fd-tr/Products/76302161.jpg?width=150&height=150"
        },
        {
          "name": "Dondurmalı Dubai Çikolatalı İrmik Helvası",
          "price": 399.0,
          "description": "Tek kişilik",
          "img": "https://images.deliveryhero.io/image/fd-tr/Products/76302389.jpg?width=150&height=150"
        },
        {
          "name": "Dondurmalı Dubai Çikolatalı İrmik Helvası (Büyük Boy)",
          "price": 565.0,
          "description": "Tek kişilik",
          "img": "https://images.deliveryhero.io/image/fd-tr/Products/76302390.jpg?width=150&height=150"
        },
        {
          "name": "Dondurmalı Lotuslu İrmik Helvası (Büyük Boy)",
          "price": 450.0,
          "description": "Tek kişilik",
          "img": "https://images.deliveryhero.io/image/fd-tr/Products/76302391.jpg?width=150&height=150"
        },
        {
          "name": "Dondurmalı Lotuslu İrmik Helvası",
          "price": 299.0,
          "description": "Tek kişilik",
          "img": "https://images.deliveryhero.io/image/fd-tr/Products/76302392.jpg?width=150&height=150"
        },
        {
          "name": "Sade İrmik Helvası (Dondurmasız) (Standart Boy)",
          "price": 199.0,
          "description": "Tek kişilik",
          "img": "https://images.deliveryhero.io/image/fd-tr/Products/76302393.jpg?width=150&height=150"
        },
        {
          "name": "Cennet Çamuru İrmik Helvası (Dondurmasız)(Büyük Boy)",
          "price": 665.0,
          "description": "Tek kişilik",
          "img": "https://images.deliveryhero.io/image/fd-tr/Products/76302449.jpg?width=150&height=150"
        },
        {
          "name": "Cennet Çamuru İrmik Helvası (Dondurmasız) (Standart Boy)",
          "price": 399.0,
          "description": "Tek kişilik",
          "img": "https://images.deliveryhero.io/image/fd-tr/Products/76302450.jpg?width=150&height=150"
        },
        {
          "name": "Sade İrmik Helvası (Dondurmasız) (Büyük Boy)",
          "price": 299.0,
          "description": "Tek kişilik",
          "img": "https://images.deliveryhero.io/image/fd-tr/Products/76302451.jpg?width=150&height=150"
        },
        {
          "name": "Çikolatalı İrmik Helvası (Dondurmasız) (Standart Boy)",
          "price": 250.0,
          "description": "Tek kişilik",
          "img": "https://micro-assets.foodora.com/img/logo-simple-ys.svg"
        },
        {
          "name": "Çikolatalı İrmik Helvası (Dondurmasız) (Büyük Boy)",
          "price": 350.0,
          "description": "Tek kişilik",
          "img": "https://images.deliveryhero.io/image/fd-tr/Products/76302487.jpg?width=150&height=150"
        },
        {
          "name": "Lotuslu İrmik Helvası (Dondurmasız) (Standart boy)",
          "price": 299.0,
          "description": "Tek kişilik",
          "img": "https://images.deliveryhero.io/image/fd-tr/Products/76302518.jpg?width=150&height=150"
        },
        {
          "name": "Dubai Çikolatalı İrmik Helvası (Dondurmasız) (Standart Boy)",
          "price": 499.0,
          "description": "Tek kişilik",
          "img": "https://images.deliveryhero.io/image/fd-tr/Products/76302519.jpg?width=150&height=150"
        },
        {
          "name": "Lotuslu İrmik Helvası (Dondurmasız) (Büyük Boy)",
          "price": 450.0,
          "description": "Tek kişilik",
          "img": "https://images.deliveryhero.io/image/fd-tr/Products/76302520.jpg?width=150&height=150"
        },
        {
          "name": "Dubai Çikolatalı İrmik Helvası (Dondurmasız) (Büyük Boy)",
          "price": 899.0,
          "description": "Tek kişilik",
          "img": "https://images.deliveryhero.io/image/fd-tr/Products/76302521.jpg?width=150&height=150"
        }
      ]
    },
    {
      "name": "İçecekler",
      "products": [
        {
          "name": "Soda (20 cl.)",
          "price": 30.0,
          "description": "Cam şişe",
          "img": "https://images.deliveryhero.io/image/fd-tr/Products/71565254.jpg?width=150&height=150"
        },
        {
          "name": "Su (50 cl.)",
          "price": 35.0,
          "description": "Pet şişe",
          "img": "https://images.deliveryhero.io/image/fd-tr/Products/71565261.jpg?width=150&height=150"
        }
      ]
    },
    {
      "name": "Aile Boyu Kiloluk Helvalar",
      "products": [
        {
          "name": "İrmik Helvası (1 kg.)",
          "price": 915.0,
          "description": "İsteğe göre tahin, yer fıstığı",
          "img": "https://images.deliveryhero.io/image/fd-tr/Products/71563114.jpg?width=150&height=150"
        },
        {
          "name": "Çikolatalı İrmik Helvası (500 gr.)",
          "price": 585.0,
          "description": "İsteğe göre tahin, yer fıstığı",
          "img": "https://images.deliveryhero.io/image/fd-tr/Products/71563246.jpg?width=150&height=150"
        },
        {
          "name": "Lotuslu İrmik Helvası (1 kg.)",
          "price": 1.5,
          "description": "Üzerine; Lotus, Lotus kırıntısı",
          "img": "https://images.deliveryhero.io/image/fd-tr/Products/71563262.jpg?width=150&height=150"
        },
        {
          "name": "Cennet Çamuru (500 gr.)",
          "price": 1.165,
          "description": "İsteğe göre tahin, yer fıstığı",
          "img": "https://images.deliveryhero.io/image/fd-tr/products/71563527.jpg?width=150&height=150"
        },
        {
          "name": "Çikolatalı İrmik Helvası (1 kg.)",
          "price": 1.165,
          "description": "İsteğe göre tahin, yer fıstığı",
          "img": "https://images.deliveryhero.io/image/fd-tr/Products/71563533.jpg?width=150&height=150"
        },
        {
          "name": "Lotuslu İrmik Helvası (500 gr.)",
          "price": 750.0,
          "description": "Üzerine; Lotus, Lotus kırıntısı",
          "img": "https://images.deliveryhero.io/image/fd-tr/Products/71563587.jpg?width=150&height=150"
        },
        {
          "name": "İrmik Helvası (500 gr.)",
          "price": 460.0,
          "description": "İsteğe göre tahin, yer fıstığı",
          "img": "https://images.deliveryhero.io/image/fd-tr/Products/71563767.jpg?width=150&height=150"
        },
        {
          "name": "Cennet Çamuru (1 kg.)",
          "price": 2.335,
          "description": "İsteğe göre tahin, yer fıstığı",
          "img": "https://images.deliveryhero.io/image/fd-tr/products/71564152.jpg?width=150&height=150"
        },
        {
          "name": "Dubai Harcı Helva (1 kg.)",
          "price": 3.335,
          "description": "1 kg. olarak servis edilir.",
          "img": "https://images.deliveryhero.io/image/fd-tr/Products/71565164.jpg?width=150&height=150"
        },
        {
          "name": "Dondurmalı Sade & Lotuslu İrmik Helvası (500 gr.)",
          "price": 750.0,
          "description": "Sade & Lotuslu irmik helvası, Maraş dondurması",
          "img": null
        },
        {
          "name": "Dondurmalı Çikolatalı Lotuslu İrmik Helvası (1 kg.)",
          "price": 1.5,
          "description": "1 kg. olarak servis edilir.",
          "img": null
        },
        {
          "name": "Dondurmalı Çikolatalı Cennet Çamuru (500 gr.)",
          "price": 1.18,
          "description": "500 gr. olarak servis edilir.",
          "img": null
        },
        {
          "name": "Dondurmalı Çikolata Cennet Çamuru (1 kg.)",
          "price": 2.34,
          "description": "1 kg. olarak servis edilir.",
          "img": null
        },
        {
          "name": "Dondurmalı Sade Çikolatalı İrmik Helvası (1 kg.)",
          "price": 1.17,
          "description": "1 kg. olarak servis edilir.",
          "img": null
        },
        {
          "name": "Dondurmalı Meyveli Sultan (1 Kg.)",
          "price": 1.17,
          "description": "1 kg. olarak servis edilir.",
          "img": null
        },
        {
          "name": "Dondurmalı Sade & Çikolatalı İrmik Helvası (500 gr.)",
          "price": 590.0,
          "description": "Sade & çikolatalı irmik helvası, Maraş dondurması",
          "img": null
        },
        {
          "name": "Dondurmalı Sade & Meyveli İrmik Helvası (500 gr.)",
          "price": 590.0,
          "description": "Sade & meyveli irmik helvası, Maraş dondurması",
          "img": null
        },
        {
          "name": "Dondurmalı Sade & Cennet Çamurlu İrmik Helvası (500 gr.)",
          "price": 1.18,
          "description": "Sade & cennet çamuru irmik helvası, Maraş dondurması",
          "img": null
        },
        {
          "name": "Dondurmalı Sade Cennet Çamuru (1 kg.)",
          "price": 2.34,
          "description": "1 kg. olarak servis edilir.",
          "img": null
        },
        {
          "name": "Dondurmalı Cennet Çamuru (500 gr.)",
          "price": 1.18,
          "description": "250 gr. cennet çamuru, 250 gr. Maraş dondurması",
          "img": null
        },
        {
          "name": "Dondurmalı Cennet Çamuru (1 kg.)",
          "price": 2.34,
          "description": "500 gr. cennet çamuru, 500 gr. Maraş dondurması ile",
          "img": null
        },
        {
          "name": "Dondurmalı Meyveli Sultan (500 gr.)",
          "price": 590.0,
          "description": "250 gr. meyveli sultan dondurması, 250 gr. Maraş dondurması ile",
          "img": null
        },
        {
          "name": "Dondurmalı Çikolatalı İrmik Helvası (1 kg.)",
          "price": 1.17,
          "description": "500 gr. çikolatalı irmik helvası, 500 gr. Maraş dondurması ile",
          "img": null
        },
        {
          "name": "Dondurmalı Sade İrmik Helvası (500 gr.)",
          "price": 465.0,
          "description": "250 gr. irmik helvası, 250 gr. Maraş dondurması ile",
          "img": null
        },
        {
          "name": "Dondurmalı Sade İrmik Helvası (1 kg.)",
          "price": 920.0,
          "description": "250 gr. irmik helvası, 250 gr. Maraş dondurması ile",
          "img": null
        },
        {
          "name": "Dondurmalı Çikolatalı İrmik Helvası (500 gr.)",
          "price": 590.0,
          "description": "250 gr. çikolatalı irmik helvası, 250 gr. Maraş dondurması ile",
          "img": null
        },
        {
          "name": "Dondurmalı Lotuslu İrmik Helvası (500 gr.)",
          "price": 750.0,
          "description": "250 gr. Lotuslu irmik helvası, 250 gr. Maraş dondurması ile",
          "img": null
        },
        {
          "name": "Dondurmalı Lotuslu-Cennet Çamuru (500 gr.)",
          "price": 1.18,
          "description": "500 gr. olarak servis edilir.",
          "img": null
        },
        {
          "name": "Dondurmalı Dubai Çikolatalı İrmik Helvası (1 kg.)",
          "price": 3.335,
          "description": "1 kg. olarak servis edilir.",
          "img": null
        },
        {
          "name": "Dondurmalı Cennet Çamuru-Meyveli İrmik Helvası (1 kg.)",
          "price": 2.34,
          "description": "1 kg. olarak servis edilir.",
          "img": null
        },
        {
          "name": "Dondurmalı Lotus-Dubai İrmik Helvası (500 gr.)",
          "price": 1.665,
          "description": "500 gr. olarak servis edilir.",
          "img": null
        },
        {
          "name": "Dondurmalı Lotus & Meyveli İrmik Helvası (1 kg.)",
          "price": 1.5,
          "description": "1 kg. olarak servis edilir.",
          "img": null
        },
        {
          "name": "Dondurmalı Lotus-Cennet Çamuru (1 kg.)",
          "price": 2.34,
          "description": "1 kg. olarak servis edilir.",
          "img": null
        },
        {
          "name": "Dondurmalı Lotus-Meyveli İrmik Helvası (500 gr.)",
          "price": 750.0,
          "description": "500 gr. olarak servis edilir.",
          "img": null
        },
        {
          "name": "Dondurmalı Cennet Çamuru-Dubai (1 kg.)",
          "price": 3.335,
          "description": "1 kg. olarak servis edilir.",
          "img": null
        },
        {
          "name": "Dondurmalı Çikolata-Dubai İrmik Helvası (500 gr.)",
          "price": 1.665,
          "description": "500 gr. olarak servis edilir.",
          "img": null
        },
        {
          "name": "Dondurmalı Lotuslu İrmik Helvası (1 kg.)",
          "price": 1.5,
          "description": "500 gr. Lotuslu irmik helvası, 500 gr. Maraş dondurması ile",
          "img": null
        },
        {
          "name": "Dondurmalı Cennet Çamuru-Dubai (500 gr.)",
          "price": 1.665,
          "description": "500 gr. olarak servis edilir.",
          "img": null
        },
        {
          "name": "Dondurmalı Lotus-Dubai (1 kg.)",
          "price": 3.335,
          "description": "1 kg. olarak servis edilir.",
          "img": null
        },
        {
          "name": "Dondurmalı Cennet Çamuru-Meyveli İrmik Helvası (500 gr.)",
          "price": 1.18,
          "description": "500 gr. olarak servis edilir.",
          "img": null
        },
        {
          "name": "Dondurmalı Çikolata & Meyveli İrmik Helvası (500 gr.)",
          "price": 590.0,
          "description": "500 gr. olarak servis edilir.",
          "img": null
        },
        {
          "name": "Dondurmalı Çikolata & Meyveli İrmik Helvası (1 kg.)",
          "price": 1.17,
          "description": "1 kg. olarak servis edilir.",
          "img": null
        },
        {
          "name": "Dondurmalı Sade Lotuslu İrmik Helvası (1 kg.)",
          "price": 1.5,
          "description": "1 kg. olarak servis edilir.",
          "img": null
        },
        {
          "name": "Dondurmalı Sade Meyveli İrmik Helvası (1 kg.)",
          "price": 1.17,
          "description": "1 kg. olarak servis edilir.",
          "img": null
        },
        {
          "name": "Dondurmalı Çikolatalı Lotuslu İrmik Helvası (500 gr.)",
          "price": 750.0,
          "description": "500 gr. olarak servis edilir.",
          "img": null
        }
      ]
    },
    {
      "name": "Poşet",
      "products": [
        {
          "name": "Poşet",
          "price": 1.0,
          "description": "Çevre Kanunu kapsamında yapılan değişiklikle her bir plastik poşetin tüketicilere 1 TL fiyat karşılığı satılması Çevre, Şehircilik ve İklim Değişikliği Bakanlığı tarafından zorunlu hale getirilmiştir. Plastik poşet talep etmeniz halinde ürünü sepete eklemeniz gerekmektedir. Sepete eklenen her bir plastik poşet için ilgili bedel tarafınızdan tahsil edilecektir.",
          "img": "https://micro-assets.foodora.com/img/logo-simple-ys.svg"
        }
      ]
    }
  ]
}