{
  "link_hash": "667d54bd",
  "scraped_at": "260528_1142",
  "restaurant_name": "Cağ Kebap",
  "link": "https://www.yemeksepeti.com/restaurant/blq1/cag-kebap-blq1",
  "categories": [
    {
      "name": "Popüler",
      "products": [
        {
          "name": "Adana Dürüm",
          "price": 350.0,
          "description": "120 gr. kuzu kıyma. Turşu, limon, maydanoz, közlenmiş biber, domates ile",
          "img": "https://images.deliveryhero.io/image/fd-tr/products/64149017.jpg?width=128&height=128"
        },
        {
          "name": "Tavuk Kıyma Dürüm",
          "price": 200.0,
          "description": "100 gr. tavuk kıyma. Biber, turşu, limon, maydanoz ile",
          "img": "https://images.deliveryhero.io/image/fd-tr/products/66101631.jpg?width=128&height=128"
        },
        {
          "name": "Tavuk Kıyma (1 kg.) (8 Şiş)",
          "price": 1.0,
          "description": "Mevsim salatası, soğan salatası, yeşillik, pişmiş biber, domates, 3 adet ekmek ile",
          "img": "https://images.deliveryhero.io/image/fd-tr/products/66101801.jpg?width=150&height=150"
        },
        {
          "name": "Karışık Izgara Tavuk",
          "price": 420.0,
          "description": "3 adet incik, 3 adet kanat, 1 şiş sarma. Turşu, yeşillik, soğan salatası, limon, maydanoz, közlenmiş biber, közlenmiş domates, salata ile",
          "img": "https://images.deliveryhero.io/image/fd-tr/Products/66101625.jfif?width=150&height=150"
        },
        {
          "name": "Adana Kebap",
          "price": 600.0,
          "description": "140 gr. Adana kebap. Ezme, tablacı salatası, salata, pişmiş domates, biber ile",
          "img": "https://images.deliveryhero.io/image/fd-tr/products/64149116.jpg?width=150&height=150"
        },
        {
          "name": "Karışık Izgara Et",
          "price": 800.0,
          "description": "100 gr. Adana kebap, 100 gr. kuşbaşı şiş, 2 adet ciğer şiş. Turşu, limon, maydanoz, mevsim salata, günün ezmesi, salata, közlenmiş domates, közlenmiş biber ile",
          "img": "https://images.deliveryhero.io/image/fd-tr/Products/66101648.jpg?width=150&height=150"
        }
      ]
    },
    {
      "name": "Coca-Cola Fırsat Menüleri",
      "products": [
        {
          "name": "Coca-Cola Fırsatı (Adana Kebap)",
          "price": 814.0,
          "description": "Adana Kebap + Coca-Cola (33 cl.)",
          "img": "https://micro-assets.foodora.com/img/logo-simple-ys.svg"
        }
      ]
    },
    {
      "name": "Izgaralar & Kebaplar",
      "products": [
        {
          "name": "Kuzu Ciğer Şiş",
          "price": 540.0,
          "description": "4şiş ciğer. Ezme salata, mevsim salata, soğan salata, pişmiş biber, soğan, domates, yeşillik, limon, ekmek ile",
          "img": "https://micro-assets.foodora.com/img/logo-simple-ys.svg"
        },
        {
          "name": "Adana Kebap",
          "price": 600.0,
          "description": "140 gr. Adana kebap. Ezme, tablacı salatası, salata, pişmiş domates, biber ile",
          "img": "https://images.deliveryhero.io/image/fd-tr/products/64149116.jpg?width=150&height=150"
        },
        {
          "name": "Kuşbaşı Şiş",
          "price": 600.0,
          "description": "200 gr. kuşbaşı şiş. Turşu, limon, maydanoz, salata ile",
          "img": "https://micro-assets.foodora.com/img/logo-simple-ys.svg"
        },
        {
          "name": "Beyti Kebap (Adanadan)",
          "price": 550.0,
          "description": "140 gr. kuzu eti. Ezme, tablacı salatası, yeşillik, limon, közlenmiş biber, közlenmiş domates, ekmek ile",
          "img": "https://images.deliveryhero.io/image/fd-tr/products/64639988.jpg?width=150&height=150"
        },
        {
          "name": "Karışık Izgara Tavuk",
          "price": 420.0,
          "description": "3 adet incik, 3 adet kanat, 1 şiş sarma. Turşu, yeşillik, soğan salatası, limon, maydanoz, közlenmiş biber, közlenmiş domates, salata ile",
          "img": "https://images.deliveryhero.io/image/fd-tr/Products/66101625.jfif?width=150&height=150"
        },
        {
          "name": "Izgara Dana Sucuk",
          "price": 400.0,
          "description": "200 gr. dana tekir sucuk. Turşu, limon, maydanoz, mevsim salata ile",
          "img": "https://images.deliveryhero.io/image/fd-tr/Products/66101626.jpg?width=150&height=150"
        },
        {
          "name": "Ciğer Şiş",
          "price": 500.0,
          "description": "6 şiş kuzu ciğer. Turşu, ezme, limon, maydanoz, pişmiş biber, domates ile",
          "img": "https://images.deliveryhero.io/image/fd-tr/products/66101643.jpg?width=150&height=150"
        },
        {
          "name": "Tavuk Kanat",
          "price": 500.0,
          "description": "6 adet kanat. Tablacı salatası, soğan salatası, köz domates, köz biber, turşu, limon ile",
          "img": "https://images.deliveryhero.io/image/fd-tr/products/66101646.jpg?width=150&height=150"
        },
        {
          "name": "Karışık Izgara Et",
          "price": 800.0,
          "description": "100 gr. Adana kebap, 100 gr. kuşbaşı şiş, 2 adet ciğer şiş. Turşu, limon, maydanoz, mevsim salata, günün ezmesi, salata, közlenmiş domates, közlenmiş biber ile",
          "img": "https://images.deliveryhero.io/image/fd-tr/Products/66101648.jpg?width=150&height=150"
        },
        {
          "name": "Tavuk Kıyma (6 Şiş)",
          "price": 1.0,
          "description": "Soğan salatası, ezme, mevsim salata, közlenmiş domates, közlenmiş biber, 3 adet ekmek, limon, yeşillik ile",
          "img": "https://images.deliveryhero.io/image/fd-tr/products/66101806.jpg?width=150&height=150"
        },
        {
          "name": "Tavuk Şiş & Kemikli Tavuk Sarma Kelebek (1 kg.)",
          "price": 900.0,
          "description": "Salata, soğan salatası, közlenmiş domates, biber, yeşillik ile",
          "img": "https://images.deliveryhero.io/image/fd-tr/products/66101812.jpg?width=150&height=150"
        }
      ]
    },
    {
      "name": "Dürümler",
      "products": [
        {
          "name": "Adana Dürüm",
          "price": 350.0,
          "description": "120 gr. kuzu kıyma. Turşu, limon, maydanoz, közlenmiş biber, domates ile",
          "img": "https://micro-assets.foodora.com/img/logo-simple-ys.svg"
        },
        {
          "name": "Kuşbaşı Şiş Dürüm",
          "price": 350.0,
          "description": "2 şiş kuşbaşı et. Turşu, limon, maydanoz, pişmiş biber, domates ile servis edilir.",
          "img": "https://micro-assets.foodora.com/img/logo-simple-ys.svg"
        },
        {
          "name": "Double Çiğ Köfte Dürüm",
          "price": 350.0,
          "description": "140 gr. çiğ köfte, göbek marul, turşu, tek lavaş, nar ekşisi",
          "img": "https://images.deliveryhero.io/image/fd-tr/products/65493039.jpg?width=150&height=150"
        },
        {
          "name": "Tavuk Kıyma Dürüm",
          "price": 200.0,
          "description": "100 gr. tavuk kıyma. Biber, turşu, limon, maydanoz ile",
          "img": "https://images.deliveryhero.io/image/fd-tr/products/66101631.jpg?width=150&height=150"
        },
        {
          "name": "Ciğer Şiş Dürüm",
          "price": 350.0,
          "description": "4 şiş kuzu ciğer, tablacı salatası, köz biber, domates. Biber turşusu, limon, maydanoz ile",
          "img": "https://images.deliveryhero.io/image/fd-tr/products/66101634.jpg?width=150&height=150"
        },
        {
          "name": "Tavuk Şiş Dürüm",
          "price": 220.0,
          "description": "Turşu, limon, maydanoz ile",
          "img": "https://images.deliveryhero.io/image/fd-tr/products/66101650.jpg?width=150&height=150"
        },
        {
          "name": "Kuşbaşı Dürüm",
          "price": 350.0,
          "description": "100 gr. kuşbaşı et, tablacı salatası. Yeşillik, limon, domates, biber ile",
          "img": "https://images.deliveryhero.io/image/fd-tr/products/66101813.jpg?width=150&height=150"
        },
        {
          "name": "Sucuk Dürüm",
          "price": 250.0,
          "description": "120 gr. sucuk, tablacı salatası. Yeşillik, turşu ile",
          "img": "https://images.deliveryhero.io/image/fd-tr/Products/67722871.jpg?width=150&height=150"
        }
      ]
    },
    {
      "name": "Diğer Lezzetler",
      "products": [
        {
          "name": "Çiğ Köfte (500 gr.)",
          "price": 370.0,
          "description": "Göbek marul, limon, turşu, nar ekşisi, yeşillik, 4 adet lavaş ile",
          "img": "https://micro-assets.foodora.com/img/logo-simple-ys.svg"
        }
      ]
    },
    {
      "name": "Menüler",
      "products": [
        {
          "name": "Duble Çiğ Köfte Dürüm Menü",
          "price": 450.0,
          "description": "Duble Çiğ Köfte Dürüm (140 gr. çiğ köfte, göbek marul, yeşillik, limon, nar eşkisi) + Ayran (20 cl.)",
          "img": "https://micro-assets.foodora.com/img/logo-simple-ys.svg"
        },
        {
          "name": "Tavuk Şnitzel",
          "price": 560.0,
          "description": "1 porsiyon tavuk şnitzel, patates kızartması, mevsim salatası, limon, ekmek ile servis yapılır.",
          "img": "https://images.deliveryhero.io/image/fd-tr/products/67794137.jpg?width=150&height=150"
        }
      ]
    },
    {
      "name": "İçecekler",
      "products": [
        {
          "name": "Coca-Cola Zero Sugar (33 cl.)",
          "price": 75.0,
          "description": "Kutu içecek",
          "img": "https://micro-assets.foodora.com/img/logo-simple-ys.svg"
        },
        {
          "name": "Coca-Cola (33 cl.)",
          "price": 75.0,
          "description": "Kutu içecek",
          "img": "https://micro-assets.foodora.com/img/logo-simple-ys.svg"
        },
        {
          "name": "Coca-Cola Light (33 cl.)",
          "price": 75.0,
          "description": "Kutu içecek",
          "img": "https://images.deliveryhero.io/image/fd-tr/products/64171567.jpg?width=150&height=150"
        },
        {
          "name": "Fanta (33 cl.)",
          "price": 75.0,
          "description": "Kutu içecek",
          "img": "https://images.deliveryhero.io/image/fd-tr/products/64171629.jpg?width=150&height=150"
        },
        {
          "name": "Sprite (33 cl.)",
          "price": 75.0,
          "description": "Kutu içecek",
          "img": "https://images.deliveryhero.io/image/fd-tr/products/64171700.jpg?width=150&height=150"
        },
        {
          "name": "Fuse Tea (33 cl.)",
          "price": 70.0,
          "description": "Kutu içecek",
          "img": "https://images.deliveryhero.io/image/fd-tr/products/64171771.jpg?width=150&height=150"
        },
        {
          "name": "Pepsi Light (33 cl.)",
          "price": 75.0,
          "description": "Kutu içecek",
          "img": "https://images.deliveryhero.io/image/fd-tr/products/64171864.jpg?width=150&height=150"
        },
        {
          "name": "Pepsi Max (33 cl.)",
          "price": 75.0,
          "description": "Kutu içecek",
          "img": "https://images.deliveryhero.io/image/fd-tr/products/64171865.jpg?width=150&height=150"
        },
        {
          "name": "Yedigün (33 cl.)",
          "price": 75.0,
          "description": "Kutu içecek",
          "img": "https://images.deliveryhero.io/image/fd-tr/products/64171866.jpg?width=150&height=150"
        },
        {
          "name": "Fruko (33 cl.)",
          "price": 75.0,
          "description": "Kutu içecek",
          "img": "https://images.deliveryhero.io/image/fd-tr/products/64171872.jpg?width=150&height=150"
        },
        {
          "name": "Lipton Ice Tea (33 cl.)",
          "price": 75.0,
          "description": "Kutu içecek",
          "img": "https://images.deliveryhero.io/image/fd-tr/products/64171969.jpg?width=150&height=150"
        },
        {
          "name": "Şalgam Suyu (30 cl.)",
          "price": 55.0,
          "description": "Pet şişe",
          "img": "https://images.deliveryhero.io/image/fd-tr/products/64171990.jpg?width=150&height=150"
        },
        {
          "name": "Ayran (20 cl.)",
          "price": 40.0,
          "description": "Küçük boy",
          "img": "https://images.deliveryhero.io/image/fd-tr/Products/64172040.jpg?width=150&height=150"
        },
        {
          "name": "Meyveli Soda (20 cl.)",
          "price": 37.0,
          "description": "Cam şişe",
          "img": "https://images.deliveryhero.io/image/fd-tr/products/64172160.jpg?width=150&height=150"
        },
        {
          "name": "Soda (20 cl.)",
          "price": 37.0,
          "description": "Cam şişe",
          "img": "https://micro-assets.foodora.com/img/logo-simple-ys.svg"
        },
        {
          "name": "Su (50 cl.)",
          "price": 25.0,
          "description": "Pet şişe",
          "img": "https://micro-assets.foodora.com/img/logo-simple-ys.svg"
        },
        {
          "name": "Coca-Cola Light (1 L.)",
          "price": 105.0,
          "description": "Pet şişe",
          "img": "https://micro-assets.foodora.com/img/logo-simple-ys.svg"
        },
        {
          "name": "Coca-Cola Şekersiz (1 L.)",
          "price": 105.0,
          "description": "Pet şişe",
          "img": "https://images.deliveryhero.io/image/fd-tr/products/64172372.jpg?width=150&height=150"
        },
        {
          "name": "Fanta (1 L.)",
          "price": 105.0,
          "description": "Pet şişe",
          "img": "https://images.deliveryhero.io/image/fd-tr/products/64172403.jpg?width=150&height=150"
        },
        {
          "name": "Sprite (1 L.)",
          "price": 105.0,
          "description": "Pet şişe",
          "img": "https://images.deliveryhero.io/image/fd-tr/products/64172424.jpg?width=150&height=150"
        },
        {
          "name": "Pepsi (1 L.)",
          "price": 105.0,
          "description": "Pet şişe",
          "img": "https://micro-assets.foodora.com/img/logo-simple-ys.svg"
        },
        {
          "name": "Pepsi Light (1 L.)",
          "price": 105.0,
          "description": "Pet şişe",
          "img": "https://micro-assets.foodora.com/img/logo-simple-ys.svg"
        },
        {
          "name": "Pepsi Zero Sugar (1 L.)",
          "price": 105.0,
          "description": "Pet şişe",
          "img": "https://images.deliveryhero.io/image/fd-tr/products/64172437.jpg?width=150&height=150"
        },
        {
          "name": "Yedigün (1 L.)",
          "price": 105.0,
          "description": "Pet şişe",
          "img": "https://micro-assets.foodora.com/img/logo-simple-ys.svg"
        },
        {
          "name": "Fruko (1 L.)",
          "price": 105.0,
          "description": "Pet şişe",
          "img": "https://images.deliveryhero.io/image/fd-tr/products/64172495.jpg?width=150&height=150"
        },
        {
          "name": "Cappy (33 cl.)",
          "price": 120.0,
          "description": "Kutu içecek",
          "img": "https://micro-assets.foodora.com/img/logo-simple-ys.svg"
        }
      ]
    },
    {
      "name": "Kiloluk Kebaplar & Izgaralar",
      "products": [
        {
          "name": "Karışık Izgara Tavuk (1 kg.)",
          "price": 900.0,
          "description": "Mevsim salatası, soğan salatası, yeşillik, pişmiş domates, biber, 3 ekmek ile",
          "img": "https://micro-assets.foodora.com/img/logo-simple-ys.svg"
        },
        {
          "name": "Tavuk Kanat (1 kg.)",
          "price": 980.0,
          "description": "Mevsim salata, soğan salatası, yeşillik, közlenmiş biber, domates, 3 adet ekmek,",
          "img": "https://micro-assets.foodora.com/img/logo-simple-ys.svg"
        },
        {
          "name": "Adana Kebap (1 kg.)",
          "price": 2.1,
          "description": "Ezme salata, mevsim salata, soğan salata, pişmiş biber, soğan, domates, yeşillik, limon, ekmek ile",
          "img": "https://images.deliveryhero.io/image/fd-tr/products/65394235.jpg?width=150&height=150"
        },
        {
          "name": "Kuşbaşı (1 kg.)",
          "price": 2.1,
          "description": "Mevsim salata, soğan salatası, yeşillik, közlenmiş biber, közlenmiş biber, 3 adet ekmek",
          "img": "https://images.deliveryhero.io/image/fd-tr/Products/66101639.jpg?width=150&height=150"
        },
        {
          "name": "Karışık Tavuk (1 kg.)",
          "price": 1.0,
          "description": "Ezme, yeşil salata, soğan salata, közlenmiş biber, soğan, domates, yeşillik, limon, 3 adet ekmek, çiğ köfte ile",
          "img": "https://images.deliveryhero.io/image/fd-tr/Products/66101644.jfif?width=150&height=150"
        },
        {
          "name": "Tavuk Kıyma (1 kg.) (8 Şiş)",
          "price": 1.0,
          "description": "Mevsim salatası, soğan salatası, yeşillik, pişmiş biber, domates, 3 adet ekmek ile",
          "img": "https://images.deliveryhero.io/image/fd-tr/products/66101801.jpg?width=150&height=150"
        },
        {
          "name": "Tavuk Pirzola (1 kg.)",
          "price": 950.0,
          "description": "Yeşillik, mevsim salata, soğan, tablacı salatası ile",
          "img": "https://images.deliveryhero.io/image/fd-tr/Products/66757798.jpg?width=150&height=150"
        },
        {
          "name": "Et Izgara (1 kg.)",
          "price": 2.1,
          "description": "Mevsim salata, soğan, yeşillik, közlenmiş biber, közlenmiş domates, ekmek ile",
          "img": null
        },
        {
          "name": "Tavuk Kıyma (1 kg.)",
          "price": 1.0,
          "description": "Yeşil salata, soğan salatası, pişmiş domates, pişmiş biber, ezme salata, 3 adet ekmek, yeşillik, limon ile",
          "img": null
        }
      ]
    },
    {
      "name": "Ana Yemekler",
      "products": [
        {
          "name": "Tavuk Sote",
          "price": 500.0,
          "description": "Mevsim salata, yeşillik, ekmek ile",
          "img": "https://micro-assets.foodora.com/img/logo-simple-ys.svg"
        },
        {
          "name": "Et Sote",
          "price": 600.0,
          "description": "200 gr. kuzu kuşbaşı eti, soğan, biber. Yeşillik, domates ile",
          "img": "https://images.deliveryhero.io/image/fd-tr/Products/66101628.jpg?width=150&height=150"
        },
        {
          "name": "Tavuk Köfte",
          "price": 450.0,
          "description": "6 adet tavuk köfte, tablacı salatası, mevsim salatası, soğan salatası, pişmiş biber, domates, yeşillik ile",
          "img": "https://images.deliveryhero.io/image/fd-tr/Products/67722847.jpg?width=150&height=150"
        }
      ]
    },
    {
      "name": "Poşet",
      "products": [
        {
          "name": "Poşet",
          "price": 1.0,
          "description": "Çevre Kanunu kapsamında yapılan değişiklikle her bir plastik poşetin tüketicilere 1 TL fiyat karşılığı satılması Çevre, Şehircilik ve İklim Değişikliği Bakanlığı tarafından zorunlu hale getirilmiştir. Plastik poşet talep etmeniz halinde ürünü sepete eklemeniz gerekmektedir. Sepete eklenen her bir plastik poşet için ilgili bedel tarafınızdan tahsil edilecektir.",
          "img": "https://micro-assets.foodora.com/img/logo-simple-ys.svg"
        }
      ]
    }
  ]
}