{
  "link_hash": "15dca530",
  "scraped_at": "260528_0116",
  "restaurant_name": "Sweet Waffle",
  "link": "https://www.yemeksepeti.com/restaurant/a1cy/sweet-waffle-a1cy",
  "categories": [
    {
      "name": "Popüler",
      "products": [
        {
          "name": "Sweet Bowl Waffle",
          "price": 408.0,
          "description": "Brüksel hamuru üzerine; sos, meyve, süslemeler",
          "img": "https://images.deliveryhero.io/image/global-menu-service/YS_TR/vendor/a1cy/product/89317220/b16ffdf5-075f-47c1-82fa-3ab732e02c8e.jpg?width=128&height=128"
        },
        {
          "name": "Sweet Brüksel Waffle",
          "price": 408.0,
          "description": "Özel brüksel hamuruna; seçeceğiniz çikolata sosları, meyveler",
          "img": "https://images.deliveryhero.io/image/global-menu-service/YS_TR/vendor/a1cy/product/89316616/d392d071-f7ad-47f2-9dd0-6b4b940ecfc6.jpg?width=128&height=128"
        },
        {
          "name": "Sweet Çiçek Waffle",
          "price": 450.5,
          "description": "Çiçek şeklinde özel sweet taze hamur ile seçeceğiniz meyve, çikolata",
          "img": "https://images.deliveryhero.io/image/global-menu-service/YS_TR/vendor/a1cy/product/89316508/475abbe5-0612-453b-9916-3e6719a8fa55.jpg?width=150&height=150"
        }
      ]
    },
    {
      "name": "Waffles",
      "products": [
        {
          "name": "Sandwich Waffle",
          "price": 408.0,
          "description": "Sweet özel hamur üzerine; seçeceğiniz meyve, çikolata, süslemeler",
          "img": "https://micro-assets.foodora.com/img/logo-simple-ys.svg"
        },
        {
          "name": "Sweet Çiçek Waffle",
          "price": 450.5,
          "description": "Çiçek şeklinde özel sweet taze hamur ile seçeceğiniz meyve, çikolata",
          "img": "https://images.deliveryhero.io/image/global-menu-service/YS_TR/vendor/a1cy/product/89316508/475abbe5-0612-453b-9916-3e6719a8fa55.jpg?width=150&height=150"
        },
        {
          "name": "Sweet Brüksel Waffle",
          "price": 408.0,
          "description": "Özel brüksel hamuruna; seçeceğiniz çikolata sosları, meyveler",
          "img": "https://micro-assets.foodora.com/img/logo-simple-ys.svg"
        },
        {
          "name": "Sweet Bowl Waffle",
          "price": 408.0,
          "description": "Brüksel hamuru üzerine; sos, meyve, süslemeler",
          "img": "https://images.deliveryhero.io/image/global-menu-service/YS_TR/vendor/a1cy/product/89317220/b16ffdf5-075f-47c1-82fa-3ab732e02c8e.jpg?width=150&height=150"
        },
        {
          "name": "Sweet Fıstık Rüyası Waffle",
          "price": 493.0,
          "description": "Antep fıstığı aromalı Brüksel waffle hamuru, seçeceğiniz sos, meyve, süsleme",
          "img": "https://micro-assets.foodora.com/img/logo-simple-ys.svg"
        },
        {
          "name": "Sweet Special Pink Bowl Waflle",
          "price": 493.0,
          "description": "Frambuaz aromalı Brüksel waffle hamuru, seçeceğiniz sos, meyve, süsleme",
          "img": "https://micro-assets.foodora.com/img/logo-simple-ys.svg"
        }
      ]
    },
    {
      "name": "İçecekler",
      "products": [
        {
          "name": "Fuse Tea Limon (33 cl.)",
          "price": 80.75,
          "description": "Kutu içecek",
          "img": "https://micro-assets.foodora.com/img/logo-simple-ys.svg"
        },
        {
          "name": "Fuse Tea Mango Ananas (33 cl.)",
          "price": 80.75,
          "description": "Kutu içecek",
          "img": "https://micro-assets.foodora.com/img/logo-simple-ys.svg"
        },
        {
          "name": "Coca-Cola (25 cl.)",
          "price": 80.75,
          "description": "Kutu içecek",
          "img": "https://micro-assets.foodora.com/img/logo-simple-ys.svg"
        },
        {
          "name": "Coca-Cola Zero Sugar (25 cl.)",
          "price": 80.75,
          "description": "Kutu içecek",
          "img": "https://micro-assets.foodora.com/img/logo-simple-ys.svg"
        },
        {
          "name": "Sprite (33 cl.)",
          "price": 80.75,
          "description": "Kutu içecek",
          "img": "https://micro-assets.foodora.com/img/logo-simple-ys.svg"
        },
        {
          "name": "Sade Soda (20 cl.)",
          "price": 42.5,
          "description": "Cam şişe",
          "img": "https://micro-assets.foodora.com/img/logo-simple-ys.svg"
        },
        {
          "name": "Su (50 cl.)",
          "price": 34.0,
          "description": "Pet şişe",
          "img": "https://images.deliveryhero.io/image/fd-tr/Products/80432747.jpg?width=150&height=150"
        }
      ]
    },
    {
      "name": "Poşet",
      "products": [
        {
          "name": "Poşet",
          "price": 1.0,
          "description": "Çevre Kanunu kapsamında yapılan değişiklikle her bir plastik poşetin tüketicilere 1 TL fiyat karşılığı satılması Çevre, Şehircilik ve İklim Değişikliği Bakanlığı tarafından zorunlu hale getirilmiştir. Plastik poşet talep etmeniz halinde ürünü sepete eklemeniz gerekmektedir. Sepete eklenen her bir plastik poşet için ilgili bedel tarafınızdan tahsil edilecektir.",
          "img": "https://micro-assets.foodora.com/img/logo-simple-ys.svg"
        }
      ]
    },
    {
      "name": "Menüler",
      "products": [
        {
          "name": "2'li Sweet Waffle Bowl Menü",
          "price": 765.0,
          "description": "2'li Sweet Waffle Bowl + 2 Adet Coca-Cola (25 cl.)",
          "img": null
        }
      ]
    }
  ]
}